{"cameraMode":{"drawMode":0,"name":"Shaded","section":"Shading Mode"},"sceneLighting":true,"audioPlay":false,"sceneViewState":{"m_AlwaysRefresh":false,"showFog":true,"showSkybox":true,"showFlares":true,"showImageEffects":true,"showParticleSystems":true,"showVisualEffectGraphs":true,"m_FxEnabled":true},"in2DMode":false,"pivot":{"x":0.5806937217712402,"y":0.8377924561500549,"z":0.20251363515853883},"rotation":{"x":-0.014827324077486992,"y":0.9454851746559143,"z":-0.04437249153852463,"w":-0.32243582606315615},"size":0.10903938859701157,"orthographic":false}